klayout-0.30.5.data/data/klayout/py.typed
klayout/laycore.pyi
klayout/libcore.pyi
klayout/lib_layview.cpython-311-darwin.so
klayout/lib_lym.cpython-311-darwin.so
klayout/lib_img.cpython-311-darwin.so
klayout/dbcore.cpython-311-darwin.so
klayout/lib_rdb.cpython-311-darwin.so
klayout/libcore.cpython-311-darwin.so
klayout/lib_lib.cpython-311-darwin.so
klayout/lib_pex.cpython-311-darwin.so
klayout/lib_edt.cpython-311-darwin.so
klayout/lib_db.cpython-311-darwin.so
klayout/pexcore.pyi
klayout/lib_gsi.cpython-311-darwin.so
klayout/rdbcore.pyi
klayout/__init__.py
klayout/lib_ant.cpython-311-darwin.so
klayout/lib_rba.cpython-311-darwin.so
klayout/lib_tl.cpython-311-darwin.so
klayout/tlcore.cpython-311-darwin.so
klayout/py.typed
klayout/dbcore.pyi
klayout/pyacore.cpython-311-darwin.so
klayout/lib_pya.cpython-311-darwin.so
klayout/laycore.cpython-311-darwin.so
klayout/pexcore.cpython-311-darwin.so
klayout/tlcore.pyi
klayout/rdbcore.cpython-311-darwin.so
klayout/lib_laybasic.cpython-311-darwin.so
klayout/pex/__init__.py
klayout/db_plugins/lib_cif_dbpi.cpython-311-darwin.dylib
klayout/db_plugins/lib_lefdef_dbpi.cpython-311-darwin.dylib
klayout/db_plugins/lib_magic_dbpi.cpython-311-darwin.dylib
klayout/db_plugins/lib_lstream_dbpi.cpython-311-darwin.dylib
klayout/db_plugins/lib_pcb_dbpi.cpython-311-darwin.dylib
klayout/db_plugins/lib_oasis_dbpi.cpython-311-darwin.dylib
klayout/db_plugins/lib_dxf_dbpi.cpython-311-darwin.dylib
klayout/db_plugins/lib_net_tracer_dbpi.cpython-311-darwin.dylib
klayout/db_plugins/lib_maly_dbpi.cpython-311-darwin.dylib
klayout/db_plugins/lib_gds2_dbpi.cpython-311-darwin.dylib
klayout/lay/__init__.py
klayout/rdb/__init__.py
klayout/tl/__init__.py
klayout/.dylibs/libpng16.16.dylib
klayout/lib/__init__.py
klayout/db/__init__.py
klayout/db/pcell_declaration_helper.py
klayout/pya/__init__.py
klayout-0.30.5.dist-info/RECORD
klayout-0.30.5.dist-info/WHEEL
klayout-0.30.5.dist-info/top_level.txt
klayout-0.30.5.dist-info/METADATA
klayout-0.30.5.dist-info/licenses/LICENSE
pya/__init__.py
