Metadata-Version: 2.1
Name: klayout
Version: 0.30.5
Summary: KLayout standalone Python package
Home-page: https://github.com/klayout/klayout
Author: Matthias Koefferlein
Author-email: matthias@klayout.org
License: GPL-3.0-or-later
Classifier: Programming Language :: Python :: 2
Classifier: Programming Language :: Python :: 3
Classifier: Operating System :: MacOS :: MacOS X
Classifier: Operating System :: Microsoft :: Windows
Classifier: Operating System :: POSIX :: Linux
Classifier: Topic :: Scientific/Engineering :: Electronic Design Automation (EDA)
License-File: LICENSE
